pastepdb/__init__.py
pastepdb/config.py
pastepdb/pastepdb.py
pastepdb-0.0.1.dist-info/License.txt
pastepdb-0.0.1.dist-info/METADATA
pastepdb-0.0.1.dist-info/WHEEL
pastepdb-0.0.1.dist-info/top_level.txt
pastepdb-0.0.1.dist-info/RECORD
