Metadata-Version: 2.1
Name: pastepdb
Version: 0.0.1
Summary: Embedded database and easy for use
Home-page: https://pastep.com
Author: Pooria Ahmadi
Author-email: pooriababak444@gmail.com
License: MIT
Platform: UNKNOWN
Classifier: Programming Language :: Python :: 3
Classifier: License :: OSI Approved :: MIT License
Classifier: Operating System :: OS Independent
Requires-Dist: betterlog
